{"updated_at":"2026-03-10T21:00:11.025Z","count":20,"items":[{"title":"Him [v0.4.1] [Kabuki]","link":"https://f95zone.to/threads/him-v0-4-1-kabuki.235471/","threadId":235471,"pubDate":"2026-03-10T21:00:08.000Z","author":"Kabuki_","category":"Games","comments":1595,"imageUrl":"/data/news-images/235471.png"},{"title":"Lustria [Development Thread]","link":"https://f95zone.to/threads/lustria-development-thread.275677/","threadId":275677,"pubDate":"2026-03-10T20:59:59.000Z","author":"LustriaGame","category":"Programming, Development & Art","comments":143,"imageUrl":"/data/news-images/275677.png"},{"title":"Symphony of the Serpent [v.59031] [NLT Media]","link":"https://f95zone.to/threads/symphony-of-the-serpent-v-59031-nlt-media.214805/","threadId":214805,"pubDate":"2026-03-10T20:59:53.000Z","author":"Bob69","category":"Games","comments":10603,"imageUrl":"/data/news-images/214805.jpg"},{"title":"The Roommate [v0.11.11] - Walkthrough Plus+ Mod","link":"https://f95zone.to/threads/the-roommate-v0-11-11-walkthrough-plus-mod.144955/","threadId":144955,"pubDate":"2026-03-10T20:59:51.000Z","author":"Emelex","category":"Mods","comments":404,"imageUrl":"/data/news-images/144955.png"},{"title":"Monster Girl Quest Fan Remake [v0.3.1] [Unknown Developer]","link":"https://f95zone.to/threads/monster-girl-quest-fan-remake-v0-3-1-unknown-developer.11499/","threadId":11499,"pubDate":"2026-03-10T20:59:47.000Z","author":"Unknown Developer","category":"Games","comments":1252,"imageUrl":"/data/news-images/11499.png"},{"title":"TwiistedLewds Collection [2026-02-25] [TwiistedLewds]","link":"https://f95zone.to/threads/twiistedlewds-collection-2026-02-25-twiistedlewds.251110/","threadId":251110,"pubDate":"2026-03-10T20:59:35.000Z","author":"Kosumo Aphrodisia","category":"Animations & Loops","comments":111,"imageUrl":null},{"title":"Urban Demons: Remake [v0.9.2] [Urban Demons]","link":"https://f95zone.to/threads/urban-demons-remake-v0-9-2-urban-demons.210417/","threadId":210417,"pubDate":"2026-03-10T20:59:12.000Z","author":"BaasB","category":"Games","comments":5264,"imageUrl":"/data/news-images/210417.png"},{"title":"Murders &amp; Mistresses [v0.15.0.70] [Undergrad Steve]","link":"https://f95zone.to/threads/murders-mistresses-v0-15-0-70-undergrad-steve.286607/","threadId":286607,"pubDate":"2026-03-10T20:59:07.000Z","author":"BaasB","category":"Games","comments":210,"imageUrl":null},{"title":"The Legend of the Sword [v0.1] [Alexgamesandso]","link":"https://f95zone.to/threads/the-legend-of-the-sword-v0-1-alexgamesandso.290319/","threadId":290319,"pubDate":"2026-03-10T20:58:39.000Z","author":"Lerd0","category":"Games","comments":22,"imageUrl":"/data/news-images/290319.jpg"},{"title":"The Null Hypothesis [v0.9a] [Ron Chon]","link":"https://f95zone.to/threads/the-null-hypothesis-v0-9a-ron-chon.138294/","threadId":138294,"pubDate":"2026-03-10T20:58:31.000Z","author":"ronchonbon","category":"Games","comments":27514,"imageUrl":"/data/news-images/138294.png"},{"title":"Lost game","link":"https://f95zone.to/threads/lost-game.290371/","threadId":290371,"pubDate":"2026-03-10T20:58:16.000Z","author":"shwnkmp","category":"Recommendations & Identification","comments":2,"imageUrl":null},{"title":"Back Again [Rework v0.14] [BigBoy Projects]","link":"https://f95zone.to/threads/back-again-rework-v0-14-bigboy-projects.191460/","threadId":191460,"pubDate":"2026-03-10T20:57:56.000Z","author":"UncleVT","category":"Games","comments":1372,"imageUrl":"/data/news-images/191460.png"},{"title":"Kelly's Family: Older sister in law [v3.0 Alpha] [K84]","link":"https://f95zone.to/threads/kellys-family-older-sister-in-law-v3-0-alpha-k84.31956/","threadId":31956,"pubDate":"2026-03-10T20:57:52.000Z","author":"Ryahn's Slut","category":"Games","comments":209,"imageUrl":"/data/news-images/31956.jpg"},{"title":"Accord [v0.4.2] [Messiah]","link":"https://f95zone.to/threads/accord-v0-4-2-messiah.226095/","threadId":226095,"pubDate":"2026-03-10T20:57:38.000Z","author":"7767","category":"Games","comments":790,"imageUrl":"/data/news-images/226095.png"},{"title":"Eternal Storm [v0.14 Beta] [StefJonson]","link":"https://f95zone.to/threads/eternal-storm-v0-14-beta-stefjonson.245428/","threadId":245428,"pubDate":"2026-03-10T20:57:38.000Z","author":"Lerd0","category":"Games","comments":113,"imageUrl":null},{"title":"Grandma's House [Part 7 v0.98] [Moonbox]","link":"https://f95zone.to/threads/grandmas-house-part-7-v0-98-moonbox.94140/","threadId":94140,"pubDate":"2026-03-10T20:57:35.000Z","author":"MoonBox","category":"Games","comments":44924,"imageUrl":"/data/news-images/94140.jpg"},{"title":"Colette's NTR Adventure [v0.1.7D] [SleepDage]","link":"https://f95zone.to/threads/colettes-ntr-adventure-v0-1-7d-sleepdage.236627/","threadId":236627,"pubDate":"2026-03-10T20:57:25.000Z","author":"Sleepiest_Not_Dage","category":"Games","comments":1405,"imageUrl":"/data/news-images/236627.png"},{"title":"Five Nights at KinksDom [v1.5.6 + v2.5] [FNAK Developper]","link":"https://f95zone.to/threads/five-nights-at-kinksdom-v1-5-6-v2-5-fnak-developper.200338/","threadId":200338,"pubDate":"2026-03-10T20:57:09.000Z","author":"FNAK Developper","category":"Games","comments":677,"imageUrl":"/data/news-images/200338.png"},{"title":"SnowStorm [v0.11 BB] [GleenX Studio]","link":"https://f95zone.to/threads/snowstorm-v0-11-bb-gleenx-studio.102771/","threadId":102771,"pubDate":"2026-03-10T20:57:08.000Z","author":"GleenXstudio","category":"Games","comments":4193,"imageUrl":"/data/news-images/102771.png"},{"title":"Alleys Of Purple Mist [v0.0.0.7aS HotFix] [dragonbird13]","link":"https://f95zone.to/threads/alleys-of-purple-mist-v0-0-0-7as-hotfix-dragonbird13.284854/","threadId":284854,"pubDate":"2026-03-10T20:56:59.000Z","author":"dragonbird13","category":"Games","comments":108,"imageUrl":"/data/news-images/284854.jpg"}]}