{"updated_at":"2026-03-17T21:30:12.079Z","count":20,"items":[{"title":"The Awakening [v0.4.6d] [SLim Games]","link":"https://f95zone.to/threads/the-awakening-v0-4-6d-slim-games.9242/","threadId":9242,"pubDate":"2026-03-17T21:30:08.000Z","author":"7767","category":"Games","comments":9073,"imageUrl":"/data/news-images/9242.png"},{"title":"Domination Academy [v0.2 PT] [Leonelli]","link":"https://f95zone.to/threads/domination-academy-v0-2-pt-leonelli.197460/","threadId":197460,"pubDate":"2026-03-17T21:29:47.000Z","author":"Leonelli","category":"Games","comments":260,"imageUrl":"/data/news-images/197460.png"},{"title":"Perverted Masseuse and Sexually Frustated Wife [v1.4.5] [fabpura]","link":"https://f95zone.to/threads/perverted-masseuse-and-sexually-frustated-wife-v1-4-5-fabpura.280729/","threadId":280729,"pubDate":"2026-03-17T21:29:30.000Z","author":"fabpura","category":"Games","comments":243,"imageUrl":null},{"title":"One Week Away [v0.6.0] [kmmgames]","link":"https://f95zone.to/threads/one-week-away-v0-6-0-kmmgames.246512/","threadId":246512,"pubDate":"2026-03-17T21:29:27.000Z","author":"7767","category":"Games","comments":623,"imageUrl":"/data/news-images/246512.png"},{"title":"Artificial Academy 2 [MiniPPX v8] [Illusion]","link":"https://f95zone.to/threads/artificial-academy-2-minippx-v8-illusion.1336/","threadId":1336,"pubDate":"2026-03-17T21:29:27.000Z","author":"Bloo","category":"Games","comments":7544,"imageUrl":"/data/news-images/1336.png"},{"title":"Becoming Prom Queen [v0.8.0e] [The Nook Erotica]","link":"https://f95zone.to/threads/becoming-prom-queen-v0-8-0e-the-nook-erotica.188960/","threadId":188960,"pubDate":"2026-03-17T21:29:20.000Z","author":"The Nook Erotica","category":"Games","comments":1488,"imageUrl":"/data/news-images/188960.gif"},{"title":"Being a DIK [v0.11.1] [DrPinkCake]","link":"https://f95zone.to/threads/being-a-dik-v0-11-1-drpinkcake.25332/","threadId":25332,"pubDate":"2026-03-17T21:28:59.000Z","author":"N7","category":"Games","comments":403572,"imageUrl":"/data/news-images/25332.jpg"},{"title":"NTR, netorare, cuckold - resources, discussion, development","link":"https://f95zone.to/threads/ntr-netorare-cuckold-resources-discussion-development.2711/","threadId":2711,"pubDate":"2026-03-17T21:28:56.000Z","author":"CobraPL","category":"Recommendations & Identification","comments":31590,"imageUrl":null},{"title":"Whispering Ledger [v0.4.0] [WispDev]","link":"https://f95zone.to/threads/whispering-ledger-v0-4-0-wispdev.273345/","threadId":273345,"pubDate":"2026-03-17T21:28:49.000Z","author":"WispDev","category":"Games","comments":380,"imageUrl":null},{"title":"Peach Hills Division [v0.71.8] [Peach Hills]","link":"https://f95zone.to/threads/peach-hills-division-v0-71-8-peach-hills.106763/","threadId":106763,"pubDate":"2026-03-17T21:28:47.000Z","author":"BaasB","category":"Games","comments":1248,"imageUrl":"/data/news-images/106763.png"},{"title":"MILF Secrets [v0.1] [Astaros 3D]","link":"https://f95zone.to/threads/milf-secrets-v0-1-astaros-3d.291304/","threadId":291304,"pubDate":"2026-03-17T21:28:28.000Z","author":"BaasB","category":"Games","comments":22,"imageUrl":"/data/news-images/291304.png"},{"title":"\"The JOI Archive\" The joi Database Patreon exclusive SiteRip v3.1 [2024-10-14]","link":"https://f95zone.to/threads/the-joi-archive-the-joi-database-patreon-exclusive-siterip-v3-1-2024-10-14.162414/","threadId":162414,"pubDate":"2026-03-17T21:28:14.000Z","author":"Skibbybop","category":"General Discussions","comments":8473,"imageUrl":null},{"title":"A Wife's Life [v1.0.0] [Kerosine_NTR]","link":"https://f95zone.to/threads/a-wifes-life-v1-0-0-kerosine_ntr.197381/","threadId":197381,"pubDate":"2026-03-17T21:28:14.000Z","author":"Supreme_Evil","category":"Games","comments":3026,"imageUrl":"/data/news-images/197381.jpg"},{"title":"Rei and the Floating City [v1.02] [Doujin Circle Gyu!]","link":"https://f95zone.to/threads/rei-and-the-floating-city-v1-02-doujin-circle-gyu.245359/","threadId":245359,"pubDate":"2026-03-17T21:28:11.000Z","author":"dazedanon","category":"Games","comments":509,"imageUrl":"/data/news-images/245359.jpg"},{"title":"PASEC [v2.2.4] [Star vs Fallout]","link":"https://f95zone.to/threads/pasec-v2-2-4-star-vs-fallout.227961/","threadId":227961,"pubDate":"2026-03-17T21:27:54.000Z","author":"EscapesMe","category":"Games","comments":1925,"imageUrl":"/data/news-images/227961.jpg"},{"title":"A Very Full House [v0.37.6] [MetaMira]","link":"https://f95zone.to/threads/a-very-full-house-v0-37-6-metamira.129381/","threadId":129381,"pubDate":"2026-03-17T21:27:50.000Z","author":"BaasB","category":"Games","comments":4566,"imageUrl":null},{"title":"Sisterly Lust [v1.2.5 Extra] [Perverteer]","link":"https://f95zone.to/threads/sisterly-lust-v1-2-5-extra-perverteer.6547/","threadId":6547,"pubDate":"2026-03-17T21:27:44.000Z","author":"7767","category":"Games","comments":13350,"imageUrl":"/data/news-images/6547.jpg"},{"title":"Wife's Bedroom [v1.1] [aplove]","link":"https://f95zone.to/threads/wifes-bedroom-v1-1-aplove.283621/","threadId":283621,"pubDate":"2026-03-17T21:27:27.000Z","author":"Lerd0","category":"Games","comments":1840,"imageUrl":null},{"title":"New Antioch [R0.6] [TheRedMyst]","link":"https://f95zone.to/threads/new-antioch-r0-6-theredmyst.160909/","threadId":160909,"pubDate":"2026-03-17T21:27:22.000Z","author":"TheRedMyst","category":"Games","comments":1827,"imageUrl":"/data/news-images/160909.png"},{"title":"Layla: Shattered Hopes [Ep.6] [OtB Games]","link":"https://f95zone.to/threads/layla-shattered-hopes-ep-6-otb-games.254333/","threadId":254333,"pubDate":"2026-03-17T21:27:18.000Z","author":"OtB Games","category":"Games","comments":361,"imageUrl":"/data/news-images/254333.png"}]}