{"updated_at":"2026-03-11T03:15:10.031Z","count":20,"items":[{"title":"Muscle-brained Shrine Maiden Kanna Crisis in the Shinobi Village [v1.0.1] [Maruru Software]","link":"https://f95zone.to/threads/muscle-brained-shrine-maiden-kanna-crisis-in-the-shinobi-village-v1-0-1-maruru-software.289988/","threadId":289988,"pubDate":"2026-03-11T03:14:37.000Z","author":"NoodleX2","category":"Games","comments":78,"imageUrl":"/data/news-images/289988.png"},{"title":"Futa Family [v0.2.44] [Ani has Problems]","link":"https://f95zone.to/threads/futa-family-v0-2-44-ani-has-problems.125074/","threadId":125074,"pubDate":"2026-03-11T03:14:18.000Z","author":"BaasB","category":"Games","comments":2672,"imageUrl":"/data/news-images/125074.png"},{"title":"Farmer Kink [v0.24] [MuseX]","link":"https://f95zone.to/threads/farmer-kink-v0-24-musex.249656/","threadId":249656,"pubDate":"2026-03-11T03:13:49.000Z","author":"BaasB","category":"Games","comments":224,"imageUrl":"/data/news-images/249656.png"},{"title":"Japs8005 Collection [2025-12-03][Japs8005]","link":"https://f95zone.to/threads/japs8005-collection-2025-12-03-japs8005.179484/","threadId":179484,"pubDate":"2026-03-11T03:13:36.000Z","author":"rf96","category":"Animations & Loops","comments":541,"imageUrl":"/data/news-images/179484.gif"},{"title":"Superhuman [v0.99999b] [WeirdWorld]","link":"https://f95zone.to/threads/superhuman-v0-99999b-weirdworld.74436/","threadId":74436,"pubDate":"2026-03-11T03:13:18.000Z","author":"WeirdWorld","category":"Games","comments":33332,"imageUrl":"/data/news-images/74436.jpg"},{"title":"Annika's Breakout [v0.0.1] [Pelitedev]","link":"https://f95zone.to/threads/annikas-breakout-v0-0-1-pelitedev.242240/","threadId":242240,"pubDate":"2026-03-11T03:13:13.000Z","author":"Lerd0","category":"Games","comments":154,"imageUrl":"/data/news-images/242240.png"},{"title":"Shogun Trainer [Beta v0.1] [DraxlerHsk]","link":"https://f95zone.to/threads/shogun-trainer-beta-v0-1-draxlerhsk.290130/","threadId":290130,"pubDate":"2026-03-11T03:13:03.000Z","author":"DraxlerHsk","category":"Games","comments":66,"imageUrl":"/data/news-images/290130.png"},{"title":"RadRoachHD Collection [2025-08-08] [RadRoachHD]","link":"https://f95zone.to/threads/radroachhd-collection-2025-08-08-radroachhd.140965/","threadId":140965,"pubDate":"2026-03-11T03:12:50.000Z","author":"LordLegolas","category":"Animations & Loops","comments":3446,"imageUrl":"/data/news-images/140965.gif"},{"title":"Emily Does It All [Ep.2] [PurpleLineStudios]","link":"https://f95zone.to/threads/emily-does-it-all-ep-2-purplelinestudios.255573/","threadId":255573,"pubDate":"2026-03-11T03:12:46.000Z","author":"PurpleLineStudios","category":"Games","comments":126,"imageUrl":null},{"title":"Hinsdale Days [v1.22] [HinsdaleDays]","link":"https://f95zone.to/threads/hinsdale-days-v1-22-hinsdaledays.282739/","threadId":282739,"pubDate":"2026-03-11T03:12:27.000Z","author":"HinsdaleDays","category":"Games","comments":991,"imageUrl":"/data/news-images/282739.jpg"},{"title":"Shrunken Isekai [Ch.9] [xredzerox]","link":"https://f95zone.to/threads/shrunken-isekai-ch-9-xredzerox.260131/","threadId":260131,"pubDate":"2026-03-11T03:12:03.000Z","author":"Bob69","category":"Games","comments":134,"imageUrl":"/data/news-images/260131.png"},{"title":"Tomboy Supremacy [v0.10b] [Abere Lucifer]","link":"https://f95zone.to/threads/tomboy-supremacy-v0-10b-abere-lucifer.139242/","threadId":139242,"pubDate":"2026-03-11T03:11:20.000Z","author":"Abere Lucifer Productions","category":"Games","comments":7580,"imageUrl":null},{"title":"Him [v0.4.1] [Kabuki]","link":"https://f95zone.to/threads/him-v0-4-1-kabuki.235471/","threadId":235471,"pubDate":"2026-03-11T03:11:03.000Z","author":"Kabuki_","category":"Games","comments":1604,"imageUrl":"/data/news-images/235471.png"},{"title":"Pregnant Angel compilation [v1.0] [alons_factory]","link":"https://f95zone.to/threads/pregnant-angel-compilation-v1-0-alons_factory.285215/","threadId":285215,"pubDate":"2026-03-11T03:10:50.000Z","author":"Bob69","category":"Games","comments":59,"imageUrl":"/data/news-images/285215.jpg"},{"title":"!Ω Factorial Omega: My Dystopian Robot Girlfriend [v0.95.15] [Incontinent Cell]","link":"https://f95zone.to/threads/o-factorial-omega-my-dystopian-robot-girlfriend-v0-95-15-incontinent-cell.74965/","threadId":74965,"pubDate":"2026-03-11T03:10:31.000Z","author":"Incontinent Cell","category":"Games","comments":5817,"imageUrl":"/data/news-images/74965.png"},{"title":"Blackmaled Collection [2023-11-16] [Gonzo Studios/Sexy3DComics]","link":"https://f95zone.to/threads/blackmaled-collection-2023-11-16-gonzo-studios-sexy3dcomics.21890/","threadId":21890,"pubDate":"2026-03-11T03:09:58.000Z","author":"Module","category":"Comics & Stills","comments":297,"imageUrl":"/data/news-images/21890.png"},{"title":"Once Again [Ch.1] [Paraloop]","link":"https://f95zone.to/threads/once-again-ch-1-paraloop.225025/","threadId":225025,"pubDate":"2026-03-11T03:09:44.000Z","author":"BaasB","category":"Games","comments":624,"imageUrl":"/data/news-images/225025.png"},{"title":"The First Gods [v0.1.1.A] [Kaspeli]","link":"https://f95zone.to/threads/the-first-gods-v0-1-1-a-kaspeli.286010/","threadId":286010,"pubDate":"2026-03-11T03:08:48.000Z","author":"Kaspeli","category":"Games","comments":140,"imageUrl":"/data/news-images/286010.png"},{"title":"[Translation Request]  \"Mirror Inma and Devil's Seed\" [62studio]","link":"https://f95zone.to/threads/translation-request-mirror-inma-and-devils-seed-62studio.191042/","threadId":191042,"pubDate":"2026-03-11T03:08:41.000Z","author":"Deleted member 3931217","category":"Request","comments":706,"imageUrl":"/data/news-images/191042.jpg"},{"title":"Sorcery Kingdom [v1.04] [Anmitsuya]","link":"https://f95zone.to/threads/sorcery-kingdom-v1-04-anmitsuya.238667/","threadId":238667,"pubDate":"2026-03-11T03:08:33.000Z","author":"hentify.net","category":"Games","comments":187,"imageUrl":"/data/news-images/238667.jpg"}]}