{"updated_at":"2026-03-20T16:15:11.049Z","count":20,"items":[{"title":"Anthro Heat [v1.3.0 Test] [Edef]","link":"https://f95zone.to/threads/anthro-heat-v1-3-0-test-edef.62348/","threadId":62348,"pubDate":"2026-03-20T16:15:04.000Z","author":"FreakyHD","category":"Games","comments":8000,"imageUrl":"/data/news-images/62348.jpg"},{"title":"Dark Vengeance [v0.2] [PutoAmo]","link":"https://f95zone.to/threads/dark-vengeance-v0-2-putoamo.270180/","threadId":270180,"pubDate":"2026-03-20T16:14:53.000Z","author":"natalie.whiteboi","category":"Games","comments":94,"imageUrl":null},{"title":"Lilith's Throne [v0.4.11.3 Hotfix] [Innoxia]","link":"https://f95zone.to/threads/liliths-throne-v0-4-11-3-hotfix-innoxia.3564/","threadId":3564,"pubDate":"2026-03-20T16:14:52.000Z","author":"Waaifu","category":"Games","comments":21115,"imageUrl":"/data/news-images/3564.png"},{"title":"MILF Obsession [v0.3.0] [DanGames]","link":"https://f95zone.to/threads/milf-obsession-v0-3-0-dangames.262710/","threadId":262710,"pubDate":"2026-03-20T16:14:36.000Z","author":"BaasB","category":"Games","comments":1045,"imageUrl":"/data/news-images/262710.png"},{"title":"Echoes of Youth [v1.0 RELEASE] [Erobyte Games]","link":"https://f95zone.to/threads/echoes-of-youth-v1-0-release-erobyte-games.278204/","threadId":278204,"pubDate":"2026-03-20T16:14:26.000Z","author":"Er0byte Games","category":"Games","comments":33,"imageUrl":"/data/news-images/278204.png"},{"title":"Shattered Minds [v0.24 Beta] [eXtasy Games]","link":"https://f95zone.to/threads/shattered-minds-v0-24-beta-extasy-games.146721/","threadId":146721,"pubDate":"2026-03-20T16:14:12.000Z","author":"eXtasy Games","category":"Games","comments":5542,"imageUrl":"/data/news-images/146721.jpg"},{"title":"Monster Black Market - MBM ModLoader [0.2.4]","link":"https://f95zone.to/threads/monster-black-market-mbm-modloader-0-2-4.290109/","threadId":290109,"pubDate":"2026-03-20T16:13:29.000Z","author":"Tsygan_m249","category":"Mods","comments":40,"imageUrl":null},{"title":"A Wife's Phone [v0.8.8] [Bloody Ink/Scyxar Studios]","link":"https://f95zone.to/threads/a-wifes-phone-v0-8-8-bloody-ink-scyxar-studios.153245/","threadId":153245,"pubDate":"2026-03-20T16:13:06.000Z","author":"7767","category":"Games","comments":8685,"imageUrl":"/data/news-images/153245.png"},{"title":"Isekai Awakening [v1.93.56] [Jackie Boy]","link":"https://f95zone.to/threads/isekai-awakening-v1-93-56-jackie-boy.151635/","threadId":151635,"pubDate":"2026-03-20T16:13:02.000Z","author":"BaasB","category":"Games","comments":2399,"imageUrl":"/data/news-images/151635.png"},{"title":"CCTV SECRETS My Wife Is A Model [v0.3] [SenSec3D]","link":"https://f95zone.to/threads/cctv-secrets-my-wife-is-a-model-v0-3-sensec3d.270975/","threadId":270975,"pubDate":"2026-03-20T16:12:56.000Z","author":"SenSec3D","category":"Games","comments":314,"imageUrl":"/data/news-images/270975.png"},{"title":"Life in Alphaville [v0.7.7] [GameleaksStudio]","link":"https://f95zone.to/threads/life-in-alphaville-v0-7-7-gameleaksstudio.159056/","threadId":159056,"pubDate":"2026-03-20T16:12:46.000Z","author":"GameleaksStudio","category":"Games","comments":589,"imageUrl":"/data/news-images/159056.png"},{"title":"Lost Freedom [v0.6] [Verde]","link":"https://f95zone.to/threads/lost-freedom-v0-6-verde.230438/","threadId":230438,"pubDate":"2026-03-20T16:12:40.000Z","author":"Verde5","category":"Games","comments":620,"imageUrl":"/data/news-images/230438.gif"},{"title":"Summer Vacation! Scramble [Final + All DLC] [ILLGAMES]","link":"https://f95zone.to/threads/summer-vacation-scramble-final-all-dlc-illgames.246998/","threadId":246998,"pubDate":"2026-03-20T16:12:28.000Z","author":"CarbyneX","category":"Games","comments":1233,"imageUrl":null},{"title":"Darklust Collection [2024-11-05] [Darklust/DarkLust/DL]","link":"https://f95zone.to/threads/darklust-collection-2024-11-05-darklust-darklust-dl.45667/","threadId":45667,"pubDate":"2026-03-20T16:12:21.000Z","author":"Crazygamer43","category":"Animations & Loops","comments":4591,"imageUrl":"/data/news-images/45667.gif"},{"title":"Lovely Craft Piston Trap [v0.2.999] [Crime]","link":"https://f95zone.to/threads/lovely-craft-piston-trap-v0-2-999-crime.234768/","threadId":234768,"pubDate":"2026-03-20T16:12:16.000Z","author":"Hello Crime","category":"Games","comments":1470,"imageUrl":null},{"title":"ForceballFX Collection [2026-03-01] [ForceballFX]","link":"https://f95zone.to/threads/forceballfx-collection-2026-03-01-forceballfx.52448/","threadId":52448,"pubDate":"2026-03-20T16:12:12.000Z","author":"Maleficent","category":"Comics & Stills","comments":357,"imageUrl":null},{"title":"NTR, netorare, cuckold - resources, discussion, development","link":"https://f95zone.to/threads/ntr-netorare-cuckold-resources-discussion-development.2711/","threadId":2711,"pubDate":"2026-03-20T16:12:03.000Z","author":"CobraPL","category":"Recommendations & Identification","comments":31683,"imageUrl":null},{"title":"My Girlfriend Wants a Threesome! (I Just Hope It's with Me) [Final] [Sieglinnde]","link":"https://f95zone.to/threads/my-girlfriend-wants-a-threesome-i-just-hope-its-with-me-final-sieglinnde.258069/","threadId":258069,"pubDate":"2026-03-20T16:12:01.000Z","author":"Sieglinnde","category":"Games","comments":900,"imageUrl":"/data/news-images/258069.png"},{"title":"[Translation Request}After Summer Break She... ~Turned into a Delinquent Loving Tan Gyal Slut~","link":"https://f95zone.to/threads/translation-request-after-summer-break-she-turned-into-a-delinquent-loving-tan-gyal-slut.81317/","threadId":81317,"pubDate":"2026-03-20T16:11:52.000Z","author":"Takyoon","category":"Request","comments":28,"imageUrl":null},{"title":"Future Fragments [v1.0.6] [HentaiWriter]","link":"https://f95zone.to/threads/future-fragments-v1-0-6-hentaiwriter.1550/","threadId":1550,"pubDate":"2026-03-20T16:11:51.000Z","author":"7767","category":"Games","comments":5418,"imageUrl":"/data/news-images/1550.png"}]}