{"updated_at":"2026-03-22T10:30:12.009Z","count":20,"items":[{"title":"Watching My Wife [v0.6.1] [Illegible Mink]","link":"https://f95zone.to/threads/watching-my-wife-v0-6-1-illegible-mink.81412/","threadId":81412,"pubDate":"2026-03-22T10:29:59.000Z","author":"Illegible Mink","category":"Games","comments":5925,"imageUrl":"/data/news-images/81412.jpg"},{"title":"NTR, netorare, cuckold - resources, discussion, development","link":"https://f95zone.to/threads/ntr-netorare-cuckold-resources-discussion-development.2711/","threadId":2711,"pubDate":"2026-03-22T10:29:45.000Z","author":"CobraPL","category":"Recommendations & Identification","comments":31771,"imageUrl":null},{"title":"Super Deepthroat [v5.41a] [Konashion]","link":"https://f95zone.to/threads/super-deepthroat-v5-41a-konashion.4605/","threadId":4605,"pubDate":"2026-03-22T10:29:43.000Z","author":"Assmaster72","category":"Games","comments":215,"imageUrl":null},{"title":"AICOMI! [ILLGAMES]","link":"https://f95zone.to/threads/aicomi-illgames.271242/","threadId":271242,"pubDate":"2026-03-22T10:29:11.000Z","author":"Mrs Slaanesh","category":"General Discussions","comments":1018,"imageUrl":"/data/news-images/271242.jpg"},{"title":"Club3 Collection [2025-05-06] [♣3]","link":"https://f95zone.to/threads/club3-collection-2025-05-06-3.243878/","threadId":243878,"pubDate":"2026-03-22T10:29:06.000Z","author":"Dragon x Hunter","category":"Animations & Loops","comments":150,"imageUrl":"/data/news-images/243878.gif"},{"title":"[Translation Request] The Mask of Blue and Silver/蒼銀の仮面 [Nuko Majin]","link":"https://f95zone.to/threads/translation-request-the-mask-of-blue-and-silver-no-nuko-majin.228406/","threadId":228406,"pubDate":"2026-03-22T10:28:54.000Z","author":"Longhairlover010","category":"Request","comments":1169,"imageUrl":"/data/news-images/228406.jpg"},{"title":"My Fallen Angels [v1.0.1] [Bad Angel Games]","link":"https://f95zone.to/threads/my-fallen-angels-v1-0-1-bad-angel-games.56174/","threadId":56174,"pubDate":"2026-03-22T10:28:50.000Z","author":"BadAngelDev","category":"Games","comments":751,"imageUrl":null},{"title":"Toxic Attraction DonSilver #Cuckold 8muses forum","link":"https://f95zone.to/threads/toxic-attraction-donsilver-cuckold-8muses-forum.186283/","threadId":186283,"pubDate":"2026-03-22T10:28:39.000Z","author":"adam adm","category":"General Discussions","comments":4755,"imageUrl":null},{"title":"Imperial Chronicles [v0.12] [Lazy Monkey]","link":"https://f95zone.to/threads/imperial-chronicles-v0-12-lazy-monkey.175608/","threadId":175608,"pubDate":"2026-03-22T10:28:12.000Z","author":"Lazy_Monkey","category":"Games","comments":8743,"imageUrl":"/data/news-images/175608.gif"},{"title":"Curious Tales of Yaezujima -Rinko Kageyama's Endless Summer- [v1.5] [Azure Azurite]","link":"https://f95zone.to/threads/curious-tales-of-yaezujima-rinko-kageyamas-endless-summer-v1-5-azure-azurite.202619/","threadId":202619,"pubDate":"2026-03-22T10:27:44.000Z","author":"Bob69","category":"Games","comments":2141,"imageUrl":"/data/news-images/202619.jpg"},{"title":"Long Story Short [v0.11a0.1] [TTrickGames]","link":"https://f95zone.to/threads/long-story-short-v0-11a0-1-ttrickgames.31351/","threadId":31351,"pubDate":"2026-03-22T10:27:33.000Z","author":"TTrick","category":"Games","comments":16760,"imageUrl":"/data/news-images/31351.png"},{"title":"WICKEDp4th's Playlist","link":"https://f95zone.to/threads/wickedp4ths-playlist.121614/","threadId":121614,"pubDate":"2026-03-22T10:27:24.000Z","author":"WICKEDp4th","category":"Recommendations & Identification","comments":104,"imageUrl":null},{"title":"Big Brother Ultimate [v0.6] [WhiteSilver]","link":"https://f95zone.to/threads/big-brother-ultimate-v0-6-whitesilver.260017/","threadId":260017,"pubDate":"2026-03-22T10:27:16.000Z","author":"White Silver","category":"Games","comments":1791,"imageUrl":"/data/news-images/260017.png"},{"title":"MILF's Plaza [18b16] [Texic]","link":"https://f95zone.to/threads/milfs-plaza-18b16-texic.66273/","threadId":66273,"pubDate":"2026-03-22T10:26:36.000Z","author":"7767","category":"Games","comments":4885,"imageUrl":"/data/news-images/66273.jpg"},{"title":"3D Custom Okazu Maker [v1.0.0] [Perverted Cat Palace]","link":"https://f95zone.to/threads/3d-custom-okazu-maker-v1-0-0-perverted-cat-palace.281683/","threadId":281683,"pubDate":"2026-03-22T10:26:25.000Z","author":"Æяiк","category":"Games","comments":155,"imageUrl":"/data/news-images/281683.png"},{"title":"Italian Free Translators","link":"https://f95zone.to/threads/italian-free-translators.116378/","threadId":116378,"pubDate":"2026-03-22T10:26:12.000Z","author":"⎰ ↜ ✰ BAD 75 ✰ ↜ ⎱","category":"Translation","comments":51161,"imageUrl":null},{"title":"LonaRPG [B.0.10.7.0] [EccmA417]","link":"https://f95zone.to/threads/lonarpg-b-0-10-7-0-eccma417.49993/","threadId":49993,"pubDate":"2026-03-22T10:25:51.000Z","author":"7767","category":"Games","comments":28870,"imageUrl":"/data/news-images/49993.png"},{"title":"Lilith's Throne [v0.4.11.3 Hotfix] [Innoxia]","link":"https://f95zone.to/threads/liliths-throne-v0-4-11-3-hotfix-innoxia.3564/","threadId":3564,"pubDate":"2026-03-22T10:25:36.000Z","author":"Waaifu","category":"Games","comments":21134,"imageUrl":"/data/news-images/3564.png"},{"title":"Perverted Education [v1.3301] [April Ryan]","link":"https://f95zone.to/threads/perverted-education-v1-3301-april-ryan.1854/","threadId":1854,"pubDate":"2026-03-22T10:25:10.000Z","author":"wynin","category":"Games","comments":3078,"imageUrl":"/data/news-images/1854.png"},{"title":"Life's Payback [v2.3] [Vinkawa]","link":"https://f95zone.to/threads/lifes-payback-v2-3-vinkawa.212785/","threadId":212785,"pubDate":"2026-03-22T10:25:01.000Z","author":"Vinkawa","category":"Games","comments":4434,"imageUrl":"/data/news-images/212785.png"}]}