{"updated_at":"2026-03-21T00:45:11.008Z","count":20,"items":[{"title":"Forgotten Royals of Astella [v1.2] [Ultimate Corruption]","link":"https://f95zone.to/threads/forgotten-royals-of-astella-v1-2-ultimate-corruption.50320/","threadId":50320,"pubDate":"2026-03-21T00:45:03.000Z","author":"redknight00","category":"Games","comments":2302,"imageUrl":"/data/news-images/50320.png"},{"title":"NTR - My Life Retribution [v1.1] [Maddesu96]","link":"https://f95zone.to/threads/ntr-my-life-retribution-v1-1-maddesu96.282447/","threadId":282447,"pubDate":"2026-03-21T00:45:01.000Z","author":"Maddesu96","category":"Games","comments":153,"imageUrl":"/data/news-images/282447.jpg"},{"title":"My Naughty Daughter [v5.2.0] [RustyV]","link":"https://f95zone.to/threads/my-naughty-daughter-v5-2-0-rustyv.152233/","threadId":152233,"pubDate":"2026-03-21T00:44:44.000Z","author":"RustyV","category":"Games","comments":1956,"imageUrl":"/data/news-images/152233.jpg"},{"title":"BNWO [v0.3] [Knox_xx]","link":"https://f95zone.to/threads/bnwo-v0-3-knox_xx.283045/","threadId":283045,"pubDate":"2026-03-21T00:44:37.000Z","author":"BaasB","category":"Games","comments":315,"imageUrl":null},{"title":"Something To Write About Unbroken [Book 2 R8] [STWAdev]","link":"https://f95zone.to/threads/something-to-write-about-unbroken-book-2-r8-stwadev.85108/","threadId":85108,"pubDate":"2026-03-21T00:44:36.000Z","author":"UncleVT","category":"Games","comments":6912,"imageUrl":null},{"title":"Heart Problems [Christmas Special] [Xenorav]","link":"https://f95zone.to/threads/heart-problems-christmas-special-xenorav.63437/","threadId":63437,"pubDate":"2026-03-21T00:44:09.000Z","author":"Xenorav","category":"Games","comments":19690,"imageUrl":"/data/news-images/63437.jpg"},{"title":"Echoes of The Cataclysm [Ch.1 P1 v0.1.11] [nuii pointer]","link":"https://f95zone.to/threads/echoes-of-the-cataclysm-ch-1-p1-v0-1-11-nuii-pointer.260370/","threadId":260370,"pubDate":"2026-03-21T00:44:08.000Z","author":"Bob69","category":"Games","comments":84,"imageUrl":"/data/news-images/260370.jpg"},{"title":"Ripples [v0.8.0 Public] [Jestur]","link":"https://f95zone.to/threads/ripples-v0-8-0-public-jestur.56110/","threadId":56110,"pubDate":"2026-03-21T00:44:05.000Z","author":"7767","category":"Games","comments":15071,"imageUrl":null},{"title":"Horton Bay Stories - Jake [v0.6.4.1] [Lumphorn Games]","link":"https://f95zone.to/threads/horton-bay-stories-jake-v0-6-4-1-lumphorn-games.91159/","threadId":91159,"pubDate":"2026-03-21T00:43:38.000Z","author":"Taka@LumphornGames","category":"Games","comments":4678,"imageUrl":"/data/news-images/91159.gif"},{"title":"My Husband's Boss [Ch.2] [SC Stories]","link":"https://f95zone.to/threads/my-husbands-boss-ch-2-sc-stories.241893/","threadId":241893,"pubDate":"2026-03-21T00:43:32.000Z","author":"SC Stories","category":"Games","comments":13488,"imageUrl":"/data/news-images/241893.png"},{"title":"Lustline Utopia [v0.1.3] [pixelrotdev]","link":"https://f95zone.to/threads/lustline-utopia-v0-1-3-pixelrotdev.291417/","threadId":291417,"pubDate":"2026-03-21T00:42:38.000Z","author":"pixelrotdev","category":"Games","comments":98,"imageUrl":"/data/news-images/291417.jpg"},{"title":"Shale Hill Secrets [v0.18.9b] [Love-Joint]","link":"https://f95zone.to/threads/shale-hill-secrets-v0-18-9b-love-joint.78583/","threadId":78583,"pubDate":"2026-03-21T00:42:23.000Z","author":"BaasB","category":"Games","comments":4126,"imageUrl":"/data/news-images/78583.png"},{"title":"A strange story ~An unnatural distribution notification received from my favorite distributor, Ripotan~ [Final] [VENUS]","link":"https://f95zone.to/threads/a-strange-story-an-unnatural-distribution-notification-received-from-my-favorite-distributor-ripotan-final-venus.291120/","threadId":291120,"pubDate":"2026-03-21T00:40:59.000Z","author":"Bob69","category":"Games","comments":54,"imageUrl":null},{"title":"Hidden Affairs [v0.02 EA] [HiddenAffairsDev]","link":"https://f95zone.to/threads/hidden-affairs-v0-02-ea-hiddenaffairsdev.291699/","threadId":291699,"pubDate":"2026-03-21T00:40:50.000Z","author":"BaasB","category":"Games","comments":17,"imageUrl":"/data/news-images/291699.png"},{"title":"Ultragirl in Dungeon [v1.1] [sxun]","link":"https://f95zone.to/threads/ultragirl-in-dungeon-v1-1-sxun.258741/","threadId":258741,"pubDate":"2026-03-21T00:40:43.000Z","author":"sxun7","category":"Games","comments":52,"imageUrl":"/data/news-images/258741.png"},{"title":"Peach Hills Division [v0.75.7] [Peach Hills]","link":"https://f95zone.to/threads/peach-hills-division-v0-75-7-peach-hills.106763/","threadId":106763,"pubDate":"2026-03-21T00:40:29.000Z","author":"BaasB","category":"Games","comments":1269,"imageUrl":"/data/news-images/106763.png"},{"title":"A Struggle with Sin [v0.6.1.8a] [Chyos]","link":"https://f95zone.to/threads/a-struggle-with-sin-v0-6-1-8a-chyos.32136/","threadId":32136,"pubDate":"2026-03-21T00:40:17.000Z","author":"Chyos","category":"Games","comments":45462,"imageUrl":null},{"title":"Jason, Coming of Age [v1.7.6-s] [CoeurDeCochon]","link":"https://f95zone.to/threads/jason-coming-of-age-v1-7-6-s-coeurdecochon.95537/","threadId":95537,"pubDate":"2026-03-21T00:40:02.000Z","author":"Lexie lecoeur","category":"Games","comments":3462,"imageUrl":"/data/news-images/95537.png"},{"title":"Blue Is Better 2 + OLD Games + XMAS [XMAS 2025] [Auril]","link":"https://f95zone.to/threads/blue-is-better-2-old-games-xmas-xmas-2025-auril.62363/","threadId":62363,"pubDate":"2026-03-21T00:39:34.000Z","author":"Mrs Slaanesh","category":"Games","comments":2241,"imageUrl":null},{"title":"Pixel3D Collection [2025-08-08] [Pixel3D]","link":"https://f95zone.to/threads/pixel3d-collection-2025-08-08-pixel3d.241656/","threadId":241656,"pubDate":"2026-03-21T00:39:20.000Z","author":"RavenOfOld","category":"Animations & Loops","comments":718,"imageUrl":"/data/news-images/241656.gif"}]}