{"updated_at":"2026-03-27T07:00:11.875Z","count":20,"items":[{"title":"Thorns Beneath the Wings [v0.14] [Aleksandr 14]","link":"https://f95zone.to/threads/thorns-beneath-the-wings-v0-14-aleksandr-14.257155/","threadId":257155,"pubDate":"2026-03-27T06:59:57.000Z","author":"Arshavinstyle","category":"Games","comments":1030,"imageUrl":"/data/news-images/257155.jpg"},{"title":"Cuckold my brother's wife [Final] [POISON MOTION]","link":"https://f95zone.to/threads/cuckold-my-brothers-wife-final-poison-motion.291836/","threadId":291836,"pubDate":"2026-03-27T06:59:55.000Z","author":"Æяiк","category":"Games","comments":59,"imageUrl":null},{"title":"Black Balance Collapse [Ch.3.64.92] [BlackBalance]","link":"https://f95zone.to/threads/black-balance-collapse-ch-3-64-92-blackbalance.277432/","threadId":277432,"pubDate":"2026-03-27T06:59:53.000Z","author":"Black Balance","category":"Games","comments":455,"imageUrl":"/data/news-images/277432.png"},{"title":"Symphony of the Serpent [v.60032] [NLT Media]","link":"https://f95zone.to/threads/symphony-of-the-serpent-v-60032-nlt-media.214805/","threadId":214805,"pubDate":"2026-03-27T06:59:38.000Z","author":"Bob69","category":"Games","comments":10816,"imageUrl":"/data/news-images/214805.jpg"},{"title":"Need recent SDT Games","link":"https://f95zone.to/threads/need-recent-sdt-games.292515/","threadId":292515,"pubDate":"2026-03-27T06:59:32.000Z","author":"wolveser","category":"Request","comments":0,"imageUrl":null},{"title":"Hey Phil [2025-12-15] [GFC Studio]","link":"https://f95zone.to/threads/hey-phil-2025-12-15-gfc-studio.161623/","threadId":161623,"pubDate":"2026-03-27T06:59:22.000Z","author":"BaasB","category":"Games","comments":718,"imageUrl":"/data/news-images/161623.jpg"},{"title":"Artificial Academy 2 [MiniPPX v8] [Illusion]","link":"https://f95zone.to/threads/artificial-academy-2-minippx-v8-illusion.1336/","threadId":1336,"pubDate":"2026-03-27T06:59:15.000Z","author":"Bloo","category":"Games","comments":7560,"imageUrl":"/data/news-images/1336.png"},{"title":"Paradise Lust 3 [v0.5.0c] [Flexible Media]","link":"https://f95zone.to/threads/paradise-lust-3-v0-5-0c-flexible-media.281972/","threadId":281972,"pubDate":"2026-03-27T06:58:47.000Z","author":"Droid Productions","category":"Games","comments":141,"imageUrl":null},{"title":"[Translation Request] The suffering of Ayame, the head of a samurai family  [Bloomflash] [RJ01572594]","link":"https://f95zone.to/threads/translation-request-the-suffering-of-ayame-the-head-of-a-samurai-family-bloomflash-rj01572594.290758/","threadId":290758,"pubDate":"2026-03-27T06:58:26.000Z","author":"EvenForgottenMyName","category":"Request","comments":79,"imageUrl":"/data/news-images/290758.png"},{"title":"Origin Story [S2 v0.9.3] [JDOR]","link":"https://f95zone.to/threads/origin-story-s2-v0-9-3-jdor.183779/","threadId":183779,"pubDate":"2026-03-27T06:58:13.000Z","author":"Jacquesdor","category":"Games","comments":8835,"imageUrl":"/data/news-images/183779.png"},{"title":"[Translation Request] Yuukan Madam Club | 有閑夫人倶楽部 [EMPRESS]","link":"https://f95zone.to/threads/translation-request-yuukan-madam-club-empress.290094/","threadId":290094,"pubDate":"2026-03-27T06:57:46.000Z","author":"faresfares","category":"Translation","comments":11,"imageUrl":"/data/news-images/290094.jpg"},{"title":"A Struggle with Sin [v0.6.1.8a] [Chyos]","link":"https://f95zone.to/threads/a-struggle-with-sin-v0-6-1-8a-chyos.32136/","threadId":32136,"pubDate":"2026-03-27T06:57:36.000Z","author":"Chyos","category":"Games","comments":45567,"imageUrl":null},{"title":"My NTR Romantic Comedy [v0.1.3a] [Pengu Games]","link":"https://f95zone.to/threads/my-ntr-romantic-comedy-v0-1-3a-pengu-games.288467/","threadId":288467,"pubDate":"2026-03-27T06:57:35.000Z","author":"7767","category":"Games","comments":85,"imageUrl":"/data/news-images/288467.png"},{"title":"Stuck at Home [v0.4.0b] [Moraion]","link":"https://f95zone.to/threads/stuck-at-home-v0-4-0b-moraion.101334/","threadId":101334,"pubDate":"2026-03-27T06:57:17.000Z","author":"BaasB","category":"Games","comments":2021,"imageUrl":"/data/news-images/101334.png"},{"title":"The Wish [v0.43] [The Sex Game's Stories]","link":"https://f95zone.to/threads/the-wish-v0-43-the-sex-games-stories.117597/","threadId":117597,"pubDate":"2026-03-27T06:56:49.000Z","author":"TSGS","category":"Games","comments":1980,"imageUrl":"/data/news-images/117597.png"},{"title":"AIKO AI Companion 3D [v0.8] [AIKO AI Companion 3D]","link":"https://f95zone.to/threads/aiko-ai-companion-3d-v0-8-aiko-ai-companion-3d.284842/","threadId":284842,"pubDate":"2026-03-27T06:56:46.000Z","author":"BaasB","category":"Games","comments":75,"imageUrl":null},{"title":"My Brother's Wife [v0.13] [Beanie Guy Studio]","link":"https://f95zone.to/threads/my-brothers-wife-v0-13-beanie-guy-studio.75404/","threadId":75404,"pubDate":"2026-03-27T06:56:37.000Z","author":"Maleficent","category":"Games","comments":3136,"imageUrl":"/data/news-images/75404.png"},{"title":"Lewd Elevator [v0.1] [Moon Trilogy]","link":"https://f95zone.to/threads/lewd-elevator-v0-1-moon-trilogy.292458/","threadId":292458,"pubDate":"2026-03-27T06:56:36.000Z","author":"Moon Trilogy","category":"Games","comments":36,"imageUrl":null},{"title":"JuicyNeko Collection [2026-03-23] [Juicyneko/juicyneko1]","link":"https://f95zone.to/threads/juicyneko-collection-2026-03-23-juicyneko-juicyneko1.72041/","threadId":72041,"pubDate":"2026-03-27T06:56:27.000Z","author":"rf96","category":"Animations & Loops","comments":477,"imageUrl":null},{"title":"RDreamer Collection [2025-07-05] [RDreamer]","link":"https://f95zone.to/threads/rdreamer-collection-2025-07-05-rdreamer.253184/","threadId":253184,"pubDate":"2026-03-27T06:56:16.000Z","author":"Kosumo Aphrodisia","category":"Animations & Loops","comments":339,"imageUrl":null}]}