{"updated_at":"2026-03-15T16:00:10.816Z","count":20,"items":[{"title":"According to Sofia [v0.03.27] [GrimaGrima]","link":"https://f95zone.to/threads/according-to-sofia-v0-03-27-grimagrima.265990/","threadId":265990,"pubDate":"2026-03-15T16:00:09.000Z","author":"grima_grima","category":"Games","comments":940,"imageUrl":"/data/news-images/265990.png"},{"title":"Strip Club Wars [v2.10] [Total Fluke Studios]","link":"https://f95zone.to/threads/strip-club-wars-v2-10-total-fluke-studios.187856/","threadId":187856,"pubDate":"2026-03-15T16:00:04.000Z","author":"TotalFluke","category":"Games","comments":7330,"imageUrl":"/data/news-images/187856.jpg"},{"title":"CUSTOM ORDER MAID 3D2 It's a Night Magic [Vanilla Repack R10] [KISS]","link":"https://f95zone.to/threads/custom-order-maid-3d2-its-a-night-magic-vanilla-repack-r10-kiss.34314/","threadId":34314,"pubDate":"2026-03-15T15:59:44.000Z","author":"Papa Ernie","category":"Games","comments":5909,"imageUrl":"/data/news-images/34314.jpg"},{"title":"The Only Doe [v0.03] [Madd5]","link":"https://f95zone.to/threads/the-only-doe-v0-03-madd5.283737/","threadId":283737,"pubDate":"2026-03-15T15:59:31.000Z","author":"Madd5","category":"Games","comments":453,"imageUrl":null},{"title":"Sonata [v0.5e] [GlossandGlamour]","link":"https://f95zone.to/threads/sonata-v0-5e-glossandglamour.250503/","threadId":250503,"pubDate":"2026-03-15T15:59:19.000Z","author":"Arshavinstyle","category":"Games","comments":44,"imageUrl":"/data/news-images/250503.jpg"},{"title":"BlackJack &amp; Hookups [v8.0] [OP'sGayLover]","link":"https://f95zone.to/threads/blackjack-hookups-v8-0-opsgaylover.273249/","threadId":273249,"pubDate":"2026-03-15T15:59:11.000Z","author":"OPsgaylover","category":"Games","comments":75,"imageUrl":"/data/news-images/273249.jpg"},{"title":"The Home of Pleasure [Ep.3 P1 v0.3] [Whispering Eye Games]","link":"https://f95zone.to/threads/the-home-of-pleasure-ep-3-p1-v0-3-whispering-eye-games.233604/","threadId":233604,"pubDate":"2026-03-15T15:59:09.000Z","author":"averonAveron","category":"Games","comments":754,"imageUrl":"/data/news-images/233604.jpg"},{"title":"Honey Select 2 [DX R16] [Illusion]","link":"https://f95zone.to/threads/honey-select-2-dx-r16-illusion.53457/","threadId":53457,"pubDate":"2026-03-15T15:59:08.000Z","author":"Ryahn's Slut","category":"Games","comments":20878,"imageUrl":"/data/news-images/53457.jpg"},{"title":"Wyldspace [v0.3.1] [Wyldspace]","link":"https://f95zone.to/threads/wyldspace-v0-3-1-wyldspace.113363/","threadId":113363,"pubDate":"2026-03-15T15:59:01.000Z","author":"wyldspace","category":"Games","comments":818,"imageUrl":"/data/news-images/113363.png"},{"title":"Eternum [v0.9.5 Public] [Caribdis]","link":"https://f95zone.to/threads/eternum-v0-9-5-public-caribdis.93340/","threadId":93340,"pubDate":"2026-03-15T15:58:59.000Z","author":"Caribdis","category":"Games","comments":52372,"imageUrl":"/data/news-images/93340.png"},{"title":"Zhao Collection [2025-09-01] [Silver Marten Studio]","link":"https://f95zone.to/threads/zhao-collection-2025-09-01-silver-marten-studio.226077/","threadId":226077,"pubDate":"2026-03-15T15:58:35.000Z","author":"RavenOfOld","category":"Animations & Loops","comments":185,"imageUrl":"/data/news-images/226077.gif"},{"title":"Deep in Hollywood Inc. [v0.24b] [Ulysses Games]","link":"https://f95zone.to/threads/deep-in-hollywood-inc-v0-24b-ulysses-games.148209/","threadId":148209,"pubDate":"2026-03-15T15:58:18.000Z","author":"Ulysses Games","category":"Games","comments":746,"imageUrl":"/data/news-images/148209.png"},{"title":"Superheat Heroes [v1.1] [Sonpih]","link":"https://f95zone.to/threads/superheat-heroes-v1-1-sonpih.265204/","threadId":265204,"pubDate":"2026-03-15T15:58:15.000Z","author":"Lerd0","category":"Games","comments":56,"imageUrl":null},{"title":"The Way Love Goes [Chapter 36] [Naughty Skunk Games] Multi Mod [AdanGC Mods &amp; BrandyYT]","link":"https://f95zone.to/threads/the-way-love-goes-chapter-36-naughty-skunk-games-multi-mod-adangc-mods-brandyyt.88902/","threadId":88902,"pubDate":"2026-03-15T15:58:08.000Z","author":"AdanGC Mods","category":"Mods","comments":385,"imageUrl":null},{"title":"Imperial Chronicles [v0.12] [Lazy Monkey]","link":"https://f95zone.to/threads/imperial-chronicles-v0-12-lazy-monkey.175608/","threadId":175608,"pubDate":"2026-03-15T15:58:05.000Z","author":"Lazy_Monkey","category":"Games","comments":8642,"imageUrl":"/data/news-images/175608.gif"},{"title":"Koikatsu Sunshine [BetterRepack R12] [Illusion]","link":"https://f95zone.to/threads/koikatsu-sunshine-betterrepack-r12-illusion.84043/","threadId":84043,"pubDate":"2026-03-15T15:57:55.000Z","author":"K3NJ1","category":"Games","comments":5892,"imageUrl":null},{"title":"My New Life Revamp PC Cheat Mod [v1.41] [SoTN]","link":"https://f95zone.to/threads/my-new-life-revamp-pc-cheat-mod-v1-41-sotn.99249/","threadId":99249,"pubDate":"2026-03-15T15:57:46.000Z","author":"Symphony of the Night","category":"Mods","comments":1203,"imageUrl":null},{"title":"Netorase Phone [v0.32.0] [Le Stag]","link":"https://f95zone.to/threads/netorase-phone-v0-32-0-le-stag.207035/","threadId":207035,"pubDate":"2026-03-15T15:57:44.000Z","author":"ReyReiner8","category":"Games","comments":10200,"imageUrl":"/data/news-images/207035.jpg"},{"title":"Potion of Desire [v0.2] [Potion of Desire Dev]","link":"https://f95zone.to/threads/potion-of-desire-v0-2-potion-of-desire-dev.288902/","threadId":288902,"pubDate":"2026-03-15T15:57:43.000Z","author":"PotionOfDesire","category":"Games","comments":76,"imageUrl":"/data/news-images/288902.png"},{"title":"The Cradle Of Nurtured Eggs [v0.1.35a] [JaShinn]","link":"https://f95zone.to/threads/the-cradle-of-nurtured-eggs-v0-1-35a-jashinn.266826/","threadId":266826,"pubDate":"2026-03-15T15:57:37.000Z","author":"Bob69","category":"Games","comments":420,"imageUrl":"/data/news-images/266826.png"}]}