{"updated_at":"2026-03-24T05:00:09.830Z","count":20,"items":[{"title":"Photo Hunt [v0.20.2 Extra] [Moochie]","link":"https://f95zone.to/threads/photo-hunt-v0-20-2-extra-moochie.25264/","threadId":25264,"pubDate":"2026-03-24T04:59:27.000Z","author":"N7","category":"Games","comments":16694,"imageUrl":"/data/news-images/25264.png"},{"title":"AI is coming","link":"https://f95zone.to/threads/ai-is-coming.292160/","threadId":292160,"pubDate":"2026-03-24T04:59:11.000Z","author":"Jondo56","category":"General Discussions","comments":0,"imageUrl":null},{"title":"Sultry Secrets [v0.0.1] [MoonNut]","link":"https://f95zone.to/threads/sultry-secrets-v0-0-1-moonnut.292117/","threadId":292117,"pubDate":"2026-03-24T04:59:02.000Z","author":"Bob69","category":"Games","comments":30,"imageUrl":"/data/news-images/292117.png"},{"title":"Lecherix Collection [2024-02-17] [Lecherix]","link":"https://f95zone.to/threads/lecherix-collection-2024-02-17-lecherix.137907/","threadId":137907,"pubDate":"2026-03-24T04:58:51.000Z","author":"LordLegolas","category":"Animations & Loops","comments":28,"imageUrl":"/data/news-images/137907.gif"},{"title":"Night Of Revenge [v1.0.7] [D-Lis]","link":"https://f95zone.to/threads/night-of-revenge-v1-0-7-d-lis.52284/","threadId":52284,"pubDate":"2026-03-24T04:58:31.000Z","author":"Maleficent","category":"Games","comments":9460,"imageUrl":"/data/news-images/52284.png"},{"title":"Seeking Night-time School game?","link":"https://f95zone.to/threads/seeking-night-time-school-game.291998/","threadId":291998,"pubDate":"2026-03-24T04:58:30.000Z","author":"snezzey","category":"Recommendations & Identification","comments":1,"imageUrl":null},{"title":"LeafFlow [v0.02] [OneManFactory]","link":"https://f95zone.to/threads/leafflow-v0-02-onemanfactory.285586/","threadId":285586,"pubDate":"2026-03-24T04:57:56.000Z","author":"Æяiк","category":"Games","comments":129,"imageUrl":null},{"title":"PunPunn Collection [2025-07-07] [PunPunn]","link":"https://f95zone.to/threads/punpunn-collection-2025-07-07-punpunn.261488/","threadId":261488,"pubDate":"2026-03-24T04:57:50.000Z","author":"SAAVEDRA","category":"Comics & Stills","comments":111,"imageUrl":"/data/news-images/261488.gif"},{"title":"Jack-o-Nine-Tails [RM Mod] [ImperatorAugustusTertius / qwertyu12359]","link":"https://f95zone.to/threads/jack-o-nine-tails-rm-mod-imperatoraugustustertius-qwertyu12359.390/","threadId":390,"pubDate":"2026-03-24T04:57:45.000Z","author":"Deleted member 141997","category":"Games","comments":13001,"imageUrl":"/data/news-images/390.png"},{"title":"The Hard Way [v0.48.0] [Muffin Maker]","link":"https://f95zone.to/threads/the-hard-way-v0-48-0-muffin-maker.74065/","threadId":74065,"pubDate":"2026-03-24T04:57:42.000Z","author":"Deleted member 2120609","category":"Games","comments":2977,"imageUrl":"/data/news-images/74065.jpg"},{"title":"Hi","link":"https://f95zone.to/threads/hi.292159/","threadId":292159,"pubDate":"2026-03-24T04:57:41.000Z","author":"3Rocks","category":"Introduction","comments":2,"imageUrl":null},{"title":"Skello-on-Sale Collection [2025-03-07] [Skello/Skello20/Soi]","link":"https://f95zone.to/threads/skello-on-sale-collection-2025-03-07-skello-skello20-soi.75817/","threadId":75817,"pubDate":"2026-03-24T04:57:38.000Z","author":"E N I G M A","category":"Animations & Loops","comments":247,"imageUrl":null},{"title":"A Struggle with Sin [v0.6.1.8a] [Chyos]","link":"https://f95zone.to/threads/a-struggle-with-sin-v0-6-1-8a-chyos.32136/","threadId":32136,"pubDate":"2026-03-24T04:57:37.000Z","author":"Chyos","category":"Games","comments":45498,"imageUrl":null},{"title":"Wolf of Shadow [v0.7.9] [VerehrER]","link":"https://f95zone.to/threads/wolf-of-shadow-v0-7-9-verehrer.165599/","threadId":165599,"pubDate":"2026-03-24T04:57:31.000Z","author":"Waaifu","category":"Games","comments":2040,"imageUrl":"/data/news-images/165599.png"},{"title":"Jury [Ep.3 P2] [Nickle3DArt]","link":"https://f95zone.to/threads/jury-ep-3-p2-nickle3dart.155304/","threadId":155304,"pubDate":"2026-03-24T04:57:10.000Z","author":"BaasB","category":"Games","comments":760,"imageUrl":"/data/news-images/155304.png"},{"title":"Chasing Sunsets [v1.10a] [Stone Fox Studios]","link":"https://f95zone.to/threads/chasing-sunsets-v1-10a-stone-fox-studios.62625/","threadId":62625,"pubDate":"2026-03-24T04:57:09.000Z","author":"Maleficent","category":"Games","comments":19071,"imageUrl":null},{"title":"Stepping Over Oneself [v0.09] [PixelFrogFoundry]","link":"https://f95zone.to/threads/stepping-over-oneself-v0-09-pixelfrogfoundry.255872/","threadId":255872,"pubDate":"2026-03-24T04:56:39.000Z","author":"PixelFrogFoundry","category":"Games","comments":399,"imageUrl":"/data/news-images/255872.png"},{"title":"Masters of Raana [v0.8.4.10] [GrimDark]","link":"https://f95zone.to/threads/masters-of-raana-v0-8-4-10-grimdark.100207/","threadId":100207,"pubDate":"2026-03-24T04:55:59.000Z","author":"GD-studios","category":"Games","comments":24415,"imageUrl":"/data/news-images/100207.jpg"},{"title":"[Secret Flasher Manaka] Custom Missions 1.2.0 &amp; Version 2 Beta 0.5.5","link":"https://f95zone.to/threads/secret-flasher-manaka-custom-missions-1-2-0-version-2-beta-0-5-5.263276/","threadId":263276,"pubDate":"2026-03-24T04:55:50.000Z","author":"Crisp2002","category":"Mods","comments":1906,"imageUrl":null},{"title":"Life is Hard [v0.1] [DoubleLife]","link":"https://f95zone.to/threads/life-is-hard-v0-1-doublelife.291785/","threadId":291785,"pubDate":"2026-03-24T04:55:50.000Z","author":"DoubleLife","category":"Games","comments":43,"imageUrl":null}]}