{"updated_at":"2026-03-24T23:45:09.958Z","count":20,"items":[{"title":"Lia and the Gem Journey [v1.06] [Hifumi Cafe]","link":"https://f95zone.to/threads/lia-and-the-gem-journey-v1-06-hifumi-cafe.291826/","threadId":291826,"pubDate":"2026-03-24T23:44:52.000Z","author":"Bob69","category":"Games","comments":75,"imageUrl":null},{"title":"The Beautiful Game [Book One v1.0.0] [Daggum]","link":"https://f95zone.to/threads/the-beautiful-game-book-one-v1-0-0-daggum.159511/","threadId":159511,"pubDate":"2026-03-24T23:44:35.000Z","author":"Daggum Games","category":"Games","comments":1186,"imageUrl":"/data/news-images/159511.png"},{"title":"A Spell for All [v14.17d] [Cmacleod42]","link":"https://f95zone.to/threads/a-spell-for-all-v14-17d-cmacleod42.571/","threadId":571,"pubDate":"2026-03-24T23:44:33.000Z","author":"Muff Diver","category":"Games","comments":10318,"imageUrl":"/data/news-images/571.png"},{"title":"Kemono Party Requests","link":"https://f95zone.to/threads/kemono-party-requests.188349/","threadId":188349,"pubDate":"2026-03-24T23:43:56.000Z","author":"Fire117","category":"General Discussions","comments":4335,"imageUrl":null},{"title":"Dream Forge Collection [2025-03-03] [Dream_Forge]","link":"https://f95zone.to/threads/dream-forge-collection-2025-03-03-dream_forge.219610/","threadId":219610,"pubDate":"2026-03-24T23:43:39.000Z","author":"RavenOfOld","category":"Animations & Loops","comments":322,"imageUrl":"/data/news-images/219610.gif"},{"title":"Pawn Pleasure [v0.5.9] [adikt]","link":"https://f95zone.to/threads/pawn-pleasure-v0-5-9-adikt.218407/","threadId":218407,"pubDate":"2026-03-24T23:43:37.000Z","author":"adikt","category":"Games","comments":582,"imageUrl":"/data/news-images/218407.gif"},{"title":"Shut Up and Dance [Ep.1-10 Ch.2 v1.3 SE] [Boring Games]","link":"https://f95zone.to/threads/shut-up-and-dance-ep-1-10-ch-2-v1-3-se-boring-games.20072/","threadId":20072,"pubDate":"2026-03-24T23:43:20.000Z","author":"monroe","category":"Games","comments":10221,"imageUrl":"/data/news-images/20072.png"},{"title":"Mad Island [v0.5.8.2 Beta] [E-made+]","link":"https://f95zone.to/threads/mad-island-v0-5-8-2-beta-e-made.209671/","threadId":209671,"pubDate":"2026-03-24T23:43:13.000Z","author":"Supreme_Evil","category":"Games","comments":21084,"imageUrl":"/data/news-images/209671.jpg"},{"title":"Home Prisoner [Ep.4 Up.2] [Inqel Interactive]","link":"https://f95zone.to/threads/home-prisoner-ep-4-up-2-inqel-interactive.89348/","threadId":89348,"pubDate":"2026-03-24T23:42:24.000Z","author":"Souleater","category":"Games","comments":3067,"imageUrl":"/data/news-images/89348.jpg"},{"title":"Nymphomania Priestess [v0.8g] [TechnoBrake]","link":"https://f95zone.to/threads/nymphomania-priestess-v0-8g-technobrake.44110/","threadId":44110,"pubDate":"2026-03-24T23:42:18.000Z","author":"BabyYoda","category":"Games","comments":26043,"imageUrl":"/data/news-images/44110.png"},{"title":"A Sex-obsessed Brother in the Country, and his Traditional, Sickly Sister [v1.02] [Sister Position]","link":"https://f95zone.to/threads/a-sex-obsessed-brother-in-the-country-and-his-traditional-sickly-sister-v1-02-sister-position.250286/","threadId":250286,"pubDate":"2026-03-24T23:42:06.000Z","author":"Bob69","category":"Games","comments":81,"imageUrl":"/data/news-images/250286.jpg"},{"title":"The Builder [S2 R1] [VanillaRock]","link":"https://f95zone.to/threads/the-builder-s2-r1-vanillarock.101278/","threadId":101278,"pubDate":"2026-03-24T23:42:00.000Z","author":"7767","category":"Games","comments":1576,"imageUrl":"/data/news-images/101278.png"},{"title":"[Translation Request]Tenmei no Conquista [Eushully]","link":"https://f95zone.to/threads/translation-request-tenmei-no-conquista-eushully.125786/","threadId":125786,"pubDate":"2026-03-24T23:41:59.000Z","author":"MihoyoSlave","category":"Request","comments":104,"imageUrl":"/data/news-images/125786.png"},{"title":"Married Life with a Lamia [v1.0] [Xoullion]","link":"https://f95zone.to/threads/married-life-with-a-lamia-v1-0-xoullion.133801/","threadId":133801,"pubDate":"2026-03-24T23:41:38.000Z","author":"7767","category":"Games","comments":266,"imageUrl":"/data/news-images/133801.png"},{"title":"Radiant [v0.7.1] [RK Studios]","link":"https://f95zone.to/threads/radiant-v0-7-1-rk-studios.49572/","threadId":49572,"pubDate":"2026-03-24T23:41:26.000Z","author":"7767","category":"Games","comments":23462,"imageUrl":"/data/news-images/49572.png"},{"title":"XXXivilization [Ch.2.5 Fix4] [hw21]","link":"https://f95zone.to/threads/xxxivilization-ch-2-5-fix4-hw21.9224/","threadId":9224,"pubDate":"2026-03-24T23:41:03.000Z","author":"Charolastra","category":"Games","comments":1016,"imageUrl":"/data/news-images/9224.jpg"},{"title":"Pale Carnations [Ch.4 Up.6 Public] [Mutt &amp; Jeff]","link":"https://f95zone.to/threads/pale-carnations-ch-4-up-6-public-mutt-jeff.50281/","threadId":50281,"pubDate":"2026-03-24T23:40:52.000Z","author":"GIL3D","category":"Games","comments":25198,"imageUrl":"/data/news-images/50281.jpg"},{"title":"Story-first games","link":"https://f95zone.to/threads/story-first-games.86340/","threadId":86340,"pubDate":"2026-03-24T23:40:22.000Z","author":"jufot","category":"Recommendations & Identification","comments":6101,"imageUrl":null},{"title":"Reds-Fall game","link":"https://f95zone.to/threads/reds-fall-game.292230/","threadId":292230,"pubDate":"2026-03-24T23:40:08.000Z","author":"DieaBOTicle","category":"Introduction","comments":2,"imageUrl":null},{"title":"Desert Stalker [v0.20.3.1] [Zetan]","link":"https://f95zone.to/threads/desert-stalker-v0-20-3-1-zetan.68105/","threadId":68105,"pubDate":"2026-03-24T23:39:56.000Z","author":"X0R","category":"Games","comments":30063,"imageUrl":"/data/news-images/68105.png"}]}